docgenius_service/__init__.py
docgenius_service/main_service.py
docgenius_service/templates/knowledge_card.md
docgenius_service/templates/resume.md
docgenius_service-2.0.4.dist-info/METADATA
docgenius_service-2.0.4.dist-info/WHEEL
docgenius_service-2.0.4.dist-info/entry_points.txt
docgenius_service-2.0.4.dist-info/top_level.txt
docgenius_service-2.0.4.dist-info/RECORD
