Metadata-Version: 2.4
Name: docgenius-service
Version: 2.0.4
Summary: 一个AI驱动的动态文档生成服务，可将文本转换为设计精美的图片。
Author-email: DocGenius Team <contact@docgenius.com>
License: MIT
Project-URL: Homepage, https://github.com/your-org/docgenius-service
Project-URL: Documentation, https://github.com/your-org/docgenius-service#readme
Project-URL: Repository, https://github.com/your-org/docgenius-service.git
Project-URL: Issues, https://github.com/your-org/docgenius-service/issues
Keywords: ai,document,generation,mcp,service,html-to-image
Classifier: Development Status :: 4 - Beta
Classifier: Intended Audience :: Developers
Classifier: License :: OSI Approved :: MIT License
Classifier: Operating System :: OS Independent
Classifier: Programming Language :: Python :: 3
Classifier: Programming Language :: Python :: 3.10
Classifier: Programming Language :: Python :: 3.11
Classifier: Programming Language :: Python :: 3.12
Classifier: Topic :: Software Development :: Libraries :: Python Modules
Classifier: Topic :: Text Processing
Classifier: Topic :: Multimedia :: Graphics
Requires-Python: >=3.10
Requires-Dist: fastmcp
Requires-Dist: playwright
Requires-Dist: python-frontmatter
Requires-Dist: aiofiles
Provides-Extra: browsers
Requires-Dist: playwright; extra == "browsers"
